Metadata-Version: 1.2
Name: nsxramlclient-py3
Version: 2.0.8
Summary: A "pseudo dynamic" client for the VMware NSX for vSphere API that uses a RAML file describing the API as an Input to generate the API calls. Updated to python 3.
Home-page: http://github.com/vmware/nsxramlclient
Author: yfauser
Author-email: yfauser@yahoo.de
Maintainer: len
Maintainer-email: len@len.ro
License: MIT
Platform: UNKNOWN
Classifier: Development Status :: 5 - Production/Stable
Classifier: Intended Audience :: Developers
Classifier: Topic :: Software Development :: Libraries
Classifier: License :: OSI Approved :: MIT License
Classifier: Programming Language :: Python :: 3.8
